torchreg/__init__.py
torchreg/affine.py
torchreg/metrics.py
torchreg/syn.py
torchreg/utils.py
torchreg-0.1.3.dist-info/LICENSE
torchreg-0.1.3.dist-info/METADATA
torchreg-0.1.3.dist-info/WHEEL
torchreg-0.1.3.dist-info/RECORD
